uw_gradepage/VERSION
uw_gradepage/__init__.py
uw_gradepage/dao.py
uw_gradepage/grading_status.py
uw_gradepage/models.py
uw_gradepage/test.py
uw_gradepage/resources/gradepage/file/api/v1/grading_status/2013-spring-A%20A-123-AA-FBB38FE46A7C11D5A4AE0004AC494FFE
uw_gradepage/resources/gradepage/file/api/v1/grading_status/2013-spring-PHYS-123-AA-FBB38FE46A7C11D5A4AE0004AC494FFE
uw_gradepage/resources/gradepage/file/api/v1/grading_status/2013-spring-TRAIN-100-A-FBB38FE46A7C11D5A4AE0004AC494FFE
uw_gradepage/resources/gradepage/file/api/v1/grading_status/2013-spring-TRAIN-200-A-FBB38FE46A7C11D5A4AE0004AC494FFE
uw_gradepage/tests/__init__.py
uw_gradepage/tests/test_grading_status.py
uw_restclients_gradepage-1.2.5.dist-info/licenses/LICENSE
uw_restclients_gradepage-1.2.5.dist-info/METADATA
uw_restclients_gradepage-1.2.5.dist-info/WHEEL
uw_restclients_gradepage-1.2.5.dist-info/top_level.txt
uw_restclients_gradepage-1.2.5.dist-info/RECORD
